pikmin/__init__.py
pikmin/art.py
pikmin/player.py
pikmin/assets/pikmin.wav
pikmin-6.9.dist-info/METADATA
pikmin-6.9.dist-info/WHEEL
pikmin-6.9.dist-info/entry_points.txt
pikmin-6.9.dist-info/top_level.txt
pikmin-6.9.dist-info/RECORD
