Metadata-Version: 2.1
Name: pikmin
Version: 6.9
Summary: package for playing pikmin from the cli.
Home-page: https://github.com/arpy8/pikmin
Author: Masti Khor
Author-email: arpitsengar99@gmail.com
Classifier: Programming Language :: Python :: 3
Classifier: License :: OSI Approved :: MIT License
Classifier: Operating System :: OS Independent
Requires-Dist: pygame
